{
	"$schema": "https://raw.githubusercontent.com/badlogic/pi-mono/main/packages/coding-agent/src/modes/interactive/theme/theme-schema.json",
	"name": "verdant",
	"vars": {
		"primary": "#00f0d3",
		"primaryDim": "#5cd1be",
		"fg": "#cbf4ed",
		"mutedFg": "#9ca3af",
		"dimFg": "#6b7280",
		"bg": "#16171d",
		"cardBg": "#202b30",
		"mutedBg": "#1f2b30",
		"borderColor": "#4a6767",
		"borderDim": "#375656",
		"secondary": "#304345",
		"green": "#51958c",
		"red": "#e98100",
		"yellow": "#e9c400",
		"chart3": "#51958c"
	},
	"colors": {
		"accent": "primary",
		"border": "borderColor",
		"borderAccent": "primary",
		"borderMuted": "borderDim",
		"success": "#5cd1be",
		"error": "red",
		"warning": "yellow",
		"muted": "mutedFg",
		"dim": "dimFg",
		"text": "",
		"thinkingText": "mutedFg",

		"selectedBg": "secondary",
		"userMessageBg": "cardBg",
		"userMessageText": "",
		"customMessageBg": "mutedBg",
		"customMessageText": "",
		"customMessageLabel": "primaryDim",
		"toolPendingBg": "mutedBg",
		"toolSuccessBg": "#1a2e2a",
		"toolErrorBg": "#2e2218",
		"toolTitle": "primary",
		"toolOutput": "mutedFg",

		"mdHeading": "#afede4",
		"mdLink": "primaryDim",
		"mdLinkUrl": "dimFg",
		"mdCode": "primary",
		"mdCodeBlock": "fg",
		"mdCodeBlockBorder": "borderColor",
		"mdQuote": "mutedFg",
		"mdQuoteBorder": "borderDim",
		"mdHr": "borderColor",
		"mdListBullet": "primary",

		"toolDiffAdded": "#5cd1be",
		"toolDiffRemoved": "#e98100",
		"toolDiffContext": "mutedFg",

		"syntaxComment": "#6b7280",
		"syntaxKeyword": "#00f0d3",
		"syntaxFunction": "#afede4",
		"syntaxVariable": "#cbf4ed",
		"syntaxString": "#5cd1be",
		"syntaxNumber": "#e9c400",
		"syntaxType": "#01f0e3",
		"syntaxOperator": "#9ca3af",
		"syntaxPunctuation": "#9ca3af",

		"thinkingOff": "borderDim",
		"thinkingMinimal": "dimFg",
		"thinkingLow": "borderColor",
		"thinkingMedium": "chart3",
		"thinkingHigh": "primaryDim",
		"thinkingXhigh": "primary",

		"bashMode": "primaryDim"
	},
	"export": {
		"pageBg": "#12131a",
		"cardBg": "#1a2328",
		"infoBg": "#1c3a3a"
	}
}
